neuropsy/__init__.py
neuropsy/pdf_generator.py
neuropsy/questions.py
neuropsy/score_cal.py
neuropsy-0.1.1.dist-info/METADATA
neuropsy-0.1.1.dist-info/WHEEL
neuropsy-0.1.1.dist-info/entry_points.txt
neuropsy-0.1.1.dist-info/top_level.txt
neuropsy-0.1.1.dist-info/RECORD
