Metadata-Version: 2.1
Name: neuropsy
Version: 0.1.1
Summary: A package for neuropsychological tools and utilities.
Home-page: https://github.com/yourusername/neuropsy
Author: Your Name
Author-email: your.email@example.com
Classifier: Programming Language :: Python :: 3
Classifier: License :: OSI Approved :: MIT License
Classifier: Operating System :: OS Independent
Requires-Python: >=3.6
Requires-Dist: PySide6
Requires-Dist: reportlab
